{"label":"Joint","comment":"The anatomical location at which two or more bones make contact.","subTypeOf":["https://schema.org/AnatomicalStructure"],"subTypes":null,"properties":["https://schema.org/additionalType","https://schema.org/alternateName","https://schema.org/associatedPathophysiology","https://schema.org/biomechnicalClass","https://schema.org/bodyLocation","https://schema.org/code","https://schema.org/connectedTo","https://schema.org/description","https://schema.org/diagram","https://schema.org/disambiguatingDescription","https://schema.org/functionalClass","https://schema.org/funding","https://schema.org/guideline","https://schema.org/identifier","https://schema.org/image","https://schema.org/legalStatus","https://schema.org/mainEntityOfPage","https://schema.org/medicineSystem","https://schema.org/name","https://schema.org/partOfSystem","https://schema.org/potentialAction","https://schema.org/recognizingAuthority","https://schema.org/relatedCondition","https://schema.org/relatedTherapy","https://schema.org/relevantSpecialty","https://schema.org/sameAs","https://schema.org/structuralClass","https://schema.org/study","https://schema.org/subStructure","https://schema.org/subjectOf","https://schema.org/url"],"supersedes":null,"supersededBy":null,"partOf":null,"id":"https://schema.org/Joint"}